MANIFEST.in
README.rst
modulelauncher.py
setup.py
module_launcher.egg-info/PKG-INFO
module_launcher.egg-info/SOURCES.txt
module_launcher.egg-info/dependency_links.txt
module_launcher.egg-info/entry_points.txt
module_launcher.egg-info/requires.txt
module_launcher.egg-info/top_level.txt
module_launcher.egg-info/zip-safe